xicam/NCEM/__init__.py
xicam/NCEM/ingestors/DMPlugin.py
xicam/NCEM/ingestors/EMDPlugin.py
xicam/NCEM/ingestors/MRCPlugin.py
xicam/NCEM/ingestors/SERPlugin.py
xicam/NCEM/ingestors/TIFPlugin.py
xicam/NCEM/ingestors/__init__.py
xicam/NCEM/widgets/FFTViewerPlugin.py
xicam/NCEM/widgets/NCEMToolbar.py
xicam/NCEM/widgets/NCEMViewerPlugin.py
xicam/NCEM/widgets/__init__.py
xicam/NCEM/widgets/fourdimageview.py
xicam/NCEM/widgets/ncemimageview.py
xicam.NCEM-0.1.5.dist-info/METADATA
xicam.NCEM-0.1.5.dist-info/WHEEL
xicam.NCEM-0.1.5.dist-info/entry_points.txt
xicam.NCEM-0.1.5.dist-info/top_level.txt
xicam.NCEM-0.1.5.dist-info/RECORD
