Metadata-Version: 2.1
Name: xicam.NCEM
Version: 0.1.5
Summary: A Xi-CAM plugin for viewing NCEM data.
Home-page: https://github.com/Xi-CAM/Xi-CAM.NCEM
Author: Peter Ercius
Author-email: percius@lbl.gov
License: BSD
Keywords: Electron Microscopy data viewing and analysis
Platform: UNKNOWN
Classifier: Development Status :: 4 - Beta
Classifier: Intended Audience :: Science/Research
Classifier: Topic :: Scientific/Engineering :: Physics
Classifier: License :: OSI Approved :: BSD License
Classifier: Programming Language :: Python :: 3.6
Classifier: Programming Language :: Python :: 3.7
Classifier: Programming Language :: Python :: 3.8
Requires-Dist: ncempy (>=1.7.0)
Requires-Dist: tifffile
Requires-Dist: dask
Requires-Dist: numpy
Requires-Dist: databroker
Requires-Dist: qtpy
Requires-Dist: pyqtgraph
Requires-Dist: xicam (==2.3.0)
Requires-Dist: databroker (<2)
Requires-Dist: pyyaml (==5.4.1)
Provides-Extra: tests
Requires-Dist: pytest ; extra == 'tests'
Requires-Dist: coverage ; extra == 'tests'
